ctrutils/__init__.py
ctrutils/database/__init__.py
ctrutils/database/influxdb/InfluxdbConnection.py
ctrutils/database/influxdb/InfluxdbOperation.py
ctrutils/database/influxdb/InfluxdbUtils.py
ctrutils/database/influxdb/__init__.py
ctrutils/handler/__init__.py
ctrutils/handler/diagnostic/__init__.py
ctrutils/handler/diagnostic/error_handler.py
ctrutils/handler/logging/__init__.py
ctrutils/handler/logging/logging_handler.py
ctrutils/handler/logging/telegram_handler.py
ctrutils/template/__init__.py
ctrutils/template/backup_influxdb.py
ctrutils/template/email_sender.py
ctrutils/utils/__init__.py
ctrutils/utils/date_utils.py
ctrutils/utils/text_utils.py
ctrutils-10.0.3.dist-info/LICENSE
ctrutils-10.0.3.dist-info/METADATA
ctrutils-10.0.3.dist-info/WHEEL
ctrutils-10.0.3.dist-info/RECORD
