Metadata-Version: 2.3
Name: ctrutils
Version: 10.0.3
Summary: Libreria de utilidades varias
License: MIT
Author: CristianTacoronteRivero
Author-email: tacoronteriverocristian@gmail.com
Requires-Python: >=3.10,<4.0
Classifier: License :: OSI Approved :: MIT License
Classifier: Programming Language :: Python :: 3
Classifier: Programming Language :: Python :: 3.10
Classifier: Programming Language :: Python :: 3.11
Classifier: Programming Language :: Python :: 3.12
Classifier: Programming Language :: Python :: 3.13
Requires-Dist: influxdb (>=5.3.2,<6.0.0)
Requires-Dist: pandas (>=2.2.3,<3.0.0)
Requires-Dist: poetry-plugin-export (>=1.8.0,<2.0.0)
Requires-Dist: python-dateutil (>=2.9.0.post0,<3.0.0)
Requires-Dist: python-logging-loki (>=0.3.1,<0.4.0)
Requires-Dist: types-python-dateutil (>=2.9.0.20241003,<3.0.0.0)
Requires-Dist: unidecode (>=1.3.8,<2.0.0)
